MANIFEST.in
README.md
build.py
pyproject.toml
requirements-dev.txt
requirements.txt
setup.py
photo_steganography/__init__.py
photo_steganography/audio.py
photo_steganography/data.py
photo_steganography/image.py
photo_steganography/video.py
photo_steganography.egg-info/PKG-INFO
photo_steganography.egg-info/SOURCES.txt
photo_steganography.egg-info/dependency_links.txt
photo_steganography.egg-info/requires.txt
photo_steganography.egg-info/top_level.txt